{
  "oasisTransactions": {
    "page": 1,
    "limit": 25,
    "data": [
      {
        "hash": "b4d277d2aa5e00db74d6e067b7a4e8341eda02495ab65ed5ed32b1de6f1878f0",
        "fee": "0",
        "gas": 1170,
        "gas_price": "0",
        "height": 64353,
        "method": "registry.RegisterNode",
        "date": "2020-06-23T01:12:56Z",
        "sender": "oasis1qqhjc0phd0wg43luhly2ufsuw2h3gc5v3ukk4ku2",
        "data": {
          "type": "REGISTER_NODE",
          "id": null,
          "entity_id": null,
          "expiration": null
        }
      },
      {
        "hash": "ea4b5214b4d062efcb27f76febefae77d16f3cd1cdff781ddb3f52e22cc66a83",
        "fee": "0",
        "gas": 1170,
        "gas_price": "0",
        "height": 64365,
        "method": "registry.RegisterNode",
        "date": "2020-06-23T01:14:07Z",
        "sender": "oasis1qqhjc0phd0wg43luhly2ufsuw2h3gc5v3ukk4ku2",
        "data": {
          "type": "REGISTER_NODE",
          "id": null,
          "entity_id": null,
          "expiration": null
        }
      },
      {
        "hash": "a5ab6c95de1d4f067866e47b6f1604a347d194e02b8a70614840f32b727145cc",
        "fee": "0",
        "gas": 1170,
        "gas_price": "0",
        "height": 64375,
        "method": "registry.RegisterNode",
        "date": "2020-06-23T01:15:07Z",
        "sender": "oasis1qqhjc0phd0wg43luhly2ufsuw2h3gc5v3ukk4ku2",
        "data": {
          "type": "REGISTER_NODE",
          "id": null,
          "entity_id": null,
          "expiration": null
        }
      },
      {
        "hash": "cb674b09f736c54ab92ae12f59be486e4a27046bf3bbec6e2354a098af1ffb89",
        "fee": "0",
        "gas": 1170,
        "gas_price": "0",
        "height": 64389,
        "method": "registry.RegisterNode",
        "date": "2020-06-23T01:16:30Z",
        "sender": "oasis1qqhjc0phd0wg43luhly2ufsuw2h3gc5v3ukk4ku2",
        "data": {
          "type": "REGISTER_NODE",
          "id": null,
          "entity_id": null,
          "expiration": null
        }
      },
      {
        "hash": "1ed88a7a507613f44f2b8083fda070f926e99f2643cbcb0822e35151536b4c5b",
        "fee": "0",
        "gas": 1170,
        "gas_price": "0",
        "height": 64401,
        "method": "registry.RegisterNode",
        "date": "2020-06-23T01:17:47Z",
        "sender": "oasis1qqhjc0phd0wg43luhly2ufsuw2h3gc5v3ukk4ku2",
        "data": {
          "type": "REGISTER_NODE",
          "id": null,
          "entity_id": null,
          "expiration": null
        }
      },
      {
        "hash": "f342559b0a312d595bf4ab1187ba819647aed5fae8eb00bf55644abffcf0d882",
        "fee": "0",
        "gas": 1170,
        "gas_price": "0",
        "height": 64415,
        "method": "registry.RegisterNode",
        "date": "2020-06-23T01:19:10Z",
        "sender": "oasis1qqhjc0phd0wg43luhly2ufsuw2h3gc5v3ukk4ku2",
        "data": {
          "type": "REGISTER_NODE",
          "id": null,
          "entity_id": null,
          "expiration": null
        }
      },
      {
        "hash": "611d37ed4dc6139e65c7f82b9973b2f2e70d817948c61c6346294cd57af5e128",
        "fee": "0",
        "gas": 1170,
        "gas_price": "0",
        "height": 64430,
        "method": "registry.RegisterNode",
        "date": "2020-06-23T01:20:38Z",
        "sender": "oasis1qqhjc0phd0wg43luhly2ufsuw2h3gc5v3ukk4ku2",
        "data": {
          "type": "REGISTER_NODE",
          "id": null,
          "entity_id": null,
          "expiration": null
        }
      },
      {
        "hash": "2e3269b6d193177bb7bac8021652e45c11aa6f11ef3125ec306eff91253db3a9",
        "fee": "0",
        "gas": 1170,
        "gas_price": "0",
        "height": 64441,
        "method": "registry.RegisterNode",
        "date": "2020-06-23T01:21:44Z",
        "sender": "oasis1qqhjc0phd0wg43luhly2ufsuw2h3gc5v3ukk4ku2",
        "data": {
          "type": "REGISTER_NODE",
          "id": null,
          "entity_id": null,
          "expiration": null
        }
      },
      {
        "hash": "0529c6af58cc57d6d0ac0f5be57769459e1d4285647b394ce7b04f8c33b78ed3",
        "fee": "0",
        "gas": 1170,
        "gas_price": "0",
        "height": 64456,
        "method": "registry.RegisterNode",
        "date": "2020-06-23T01:23:12Z",
        "sender": "oasis1qqhjc0phd0wg43luhly2ufsuw2h3gc5v3ukk4ku2",
        "data": {
          "type": "REGISTER_NODE",
          "id": null,
          "entity_id": null,
          "expiration": null
        }
      },
      {
        "hash": "231d4ef41aaa5d83f873a97a820327cedf1f34118c2e83184df9dcdedfedc83b",
        "fee": "0",
        "gas": 1170,
        "gas_price": "0",
        "height": 64471,
        "method": "registry.RegisterNode",
        "date": "2020-06-23T01:24:40Z",
        "sender": "oasis1qqhjc0phd0wg43luhly2ufsuw2h3gc5v3ukk4ku2",
        "data": {
          "type": "REGISTER_NODE",
          "id": null,
          "entity_id": null,
          "expiration": null
        }
      },
      {
        "hash": "fcba85d4499958b14d07075086e66c8ccdb7b413494810443b0c8043fcd51493",
        "fee": "0",
        "gas": 1170,
        "gas_price": "0",
        "height": 64479,
        "method": "registry.RegisterNode",
        "date": "2020-06-23T01:25:27Z",
        "sender": "oasis1qqhjc0phd0wg43luhly2ufsuw2h3gc5v3ukk4ku2",
        "data": {
          "type": "REGISTER_NODE",
          "id": null,
          "entity_id": null,
          "expiration": null
        }
      },
      {
        "hash": "3d655ba41f7c66a8c392b836f78dd5f74c71c1da47481cc03921d6b701fa46d6",
        "fee": "0",
        "gas": 1170,
        "gas_price": "0",
        "height": 64494,
        "method": "registry.RegisterNode",
        "date": "2020-06-23T01:26:57Z",
        "sender": "oasis1qqhjc0phd0wg43luhly2ufsuw2h3gc5v3ukk4ku2",
        "data": {
          "type": "REGISTER_NODE",
          "id": null,
          "entity_id": null,
          "expiration": null
        }
      },
      {
        "hash": "3960ca1448133f0bcb34c9cab0bde5a58ed27bb185dc29f66916468e9c8bc1d0",
        "fee": "0",
        "gas": 1170,
        "gas_price": "0",
        "height": 64502,
        "method": "registry.RegisterNode",
        "date": "2020-06-23T01:27:43Z",
        "sender": "oasis1qqhjc0phd0wg43luhly2ufsuw2h3gc5v3ukk4ku2",
        "data": {
          "type": "REGISTER_NODE",
          "id": null,
          "entity_id": null,
          "expiration": null
        }
      },
      {
        "hash": "3311322e05e166d4e228884940ebec1e42df55713475467e5331c28b8e4f6bb9",
        "fee": "0",
        "gas": 1170,
        "gas_price": "0",
        "height": 64508,
        "method": "registry.RegisterNode",
        "date": "2020-06-23T01:28:20Z",
        "sender": "oasis1qqhjc0phd0wg43luhly2ufsuw2h3gc5v3ukk4ku2",
        "data": {
          "type": "REGISTER_NODE",
          "id": null,
          "entity_id": null,
          "expiration": null
        }
      },
      {
        "hash": "6ce0f95b09585569d44fe44ac80adfd8b30e269a5222544e297630662d6affca",
        "fee": "0",
        "gas": 1170,
        "gas_price": "0",
        "height": 64516,
        "method": "registry.RegisterNode",
        "date": "2020-06-23T01:29:06Z",
        "sender": "oasis1qqhjc0phd0wg43luhly2ufsuw2h3gc5v3ukk4ku2",
        "data": {
          "type": "REGISTER_NODE",
          "id": null,
          "entity_id": null,
          "expiration": null
        }
      },
      {
        "hash": "ff4720cca007cb6888919a6648d458d188af1ccdd27c8b43098f809c50bf2206",
        "fee": "0",
        "gas": 1170,
        "gas_price": "0",
        "height": 64521,
        "method": "registry.RegisterNode",
        "date": "2020-06-23T01:29:40Z",
        "sender": "oasis1qqhjc0phd0wg43luhly2ufsuw2h3gc5v3ukk4ku2",
        "data": {
          "type": "REGISTER_NODE",
          "id": null,
          "entity_id": null,
          "expiration": null
        }
      },
      {
        "hash": "a6b6854ec60c137d4e477ebc248ee03b6bf080c82e720d572c88b88b09cb91ae",
        "fee": "0",
        "gas": 1170,
        "gas_price": "0",
        "height": 64533,
        "method": "registry.RegisterNode",
        "date": "2020-06-23T01:30:51Z",
        "sender": "oasis1qqhjc0phd0wg43luhly2ufsuw2h3gc5v3ukk4ku2",
        "data": {
          "type": "REGISTER_NODE",
          "id": null,
          "entity_id": null,
          "expiration": null
        }
      },
      {
        "hash": "c041e348f6a2dd611f2ef8f4323f8191b2a161b22e09a428a05b30a8fca89477",
        "fee": "0",
        "gas": 1170,
        "gas_price": "0",
        "height": 64542,
        "method": "registry.RegisterNode",
        "date": "2020-06-23T01:31:44Z",
        "sender": "oasis1qqhjc0phd0wg43luhly2ufsuw2h3gc5v3ukk4ku2",
        "data": {
          "type": "REGISTER_NODE",
          "id": null,
          "entity_id": null,
          "expiration": null
        }
      },
      {
        "hash": "177c92793fd5163bbb7874aa061feb28407f34967ea992f8a6c8acc4dc6b4253",
        "fee": "0",
        "gas": 1170,
        "gas_price": "0",
        "height": 64554,
        "method": "registry.RegisterNode",
        "date": "2020-06-23T01:32:56Z",
        "sender": "oasis1qqhjc0phd0wg43luhly2ufsuw2h3gc5v3ukk4ku2",
        "data": {
          "type": "REGISTER_NODE",
          "id": null,
          "entity_id": null,
          "expiration": null
        }
      },
      {
        "hash": "538bff3daf96f5565c9a57820ae51905ac2fbc4c90cbc735f1fa29868e0ae099",
        "fee": "0",
        "gas": 1170,
        "gas_price": "0",
        "height": 64567,
        "method": "registry.RegisterNode",
        "date": "2020-06-23T01:34:13Z",
        "sender": "oasis1qqhjc0phd0wg43luhly2ufsuw2h3gc5v3ukk4ku2",
        "data": {
          "type": "REGISTER_NODE",
          "id": null,
          "entity_id": null,
          "expiration": null
        }
      },
      {
        "hash": "2a349b399583bc5f818b2773004860d19f05fb93d2505179f88698ac54e49981",
        "fee": "0",
        "gas": 1170,
        "gas_price": "0",
        "height": 64576,
        "method": "registry.RegisterNode",
        "date": "2020-06-23T01:35:08Z",
        "sender": "oasis1qqhjc0phd0wg43luhly2ufsuw2h3gc5v3ukk4ku2",
        "data": {
          "type": "REGISTER_NODE",
          "id": null,
          "entity_id": null,
          "expiration": null
        }
      },
      {
        "hash": "e8f9268d01cc640bdd3af8ca51876cd09ebdd3a548f5080fc16acc6db797c5c0",
        "fee": "0",
        "gas": 1170,
        "gas_price": "0",
        "height": 64585,
        "method": "registry.RegisterNode",
        "date": "2020-06-23T01:36:00Z",
        "sender": "oasis1qqhjc0phd0wg43luhly2ufsuw2h3gc5v3ukk4ku2",
        "data": {
          "type": "REGISTER_NODE",
          "id": null,
          "entity_id": null,
          "expiration": null
        }
      },
      {
        "hash": "c375a286197f29b219fab01e3484d78ad7dbcb67d7cf1c05f91c9b44b4cd6fc5",
        "fee": "0",
        "gas": 1170,
        "gas_price": "0",
        "height": 64598,
        "method": "registry.RegisterNode",
        "date": "2020-06-23T01:37:18Z",
        "sender": "oasis1qqhjc0phd0wg43luhly2ufsuw2h3gc5v3ukk4ku2",
        "data": {
          "type": "REGISTER_NODE",
          "id": null,
          "entity_id": null,
          "expiration": null
        }
      },
      {
        "hash": "8be14c56bcef5cb9f925b604aa8a1ff8ecaa99409b91dbca2d76bd78f50840d6",
        "fee": "0",
        "gas": 1170,
        "gas_price": "0",
        "height": 64611,
        "method": "registry.RegisterNode",
        "date": "2020-06-23T01:38:35Z",
        "sender": "oasis1qqhjc0phd0wg43luhly2ufsuw2h3gc5v3ukk4ku2",
        "data": {
          "type": "REGISTER_NODE",
          "id": null,
          "entity_id": null,
          "expiration": null
        }
      },
      {
        "hash": "231734e0e20eec7a79a4bbfa7cd336de03314658c34cfb0454386c53a2119f18",
        "fee": "0",
        "gas": 1170,
        "gas_price": "0",
        "height": 64621,
        "method": "registry.RegisterNode",
        "date": "2020-06-23T01:39:34Z",
        "sender": "oasis1qqhjc0phd0wg43luhly2ufsuw2h3gc5v3ukk4ku2",
        "data": {
          "type": "REGISTER_NODE",
          "id": null,
          "entity_id": null,
          "expiration": null
        }
      }
    ],
    "moreResultsExist": true
  }
}
